eval_mm/__init__.py
eval_mm/_version.py
eval_mm/metrics/__init__.py
eval_mm/metrics/cc_ocr_scorer.py
eval_mm/metrics/exact_match_scorer.py
eval_mm/metrics/heron_bench_scorer.py
eval_mm/metrics/jdocqa_scorer.py
eval_mm/metrics/jic_vqa_scorer.py
eval_mm/metrics/jmmmu_scorer.py
eval_mm/metrics/llm_as_a_judge_scorer.py
eval_mm/metrics/mecha_ja_scorer.py
eval_mm/metrics/mmmu_scorer.py
eval_mm/metrics/rougel_scorer.py
eval_mm/metrics/scorer.py
eval_mm/metrics/scorer_registry.py
eval_mm/metrics/substring_match_scorer.py
eval_mm/tasks/__init__.py
eval_mm/tasks/cc_ocr.py
eval_mm/tasks/cvqa.py
eval_mm/tasks/ja_multi_image_vqa.py
eval_mm/tasks/ja_vg_vqa_500.py
eval_mm/tasks/ja_vlm_bench_in_the_wild.py
eval_mm/tasks/japanese_heron_bench.py
eval_mm/tasks/jdocqa.py
eval_mm/tasks/jic_vqa.py
eval_mm/tasks/jmmmu.py
eval_mm/tasks/llava_bench_in_the_wild.py
eval_mm/tasks/mecha_ja.py
eval_mm/tasks/mmmlu.py
eval_mm/tasks/mmmu.py
eval_mm/tasks/mnist.py
eval_mm/tasks/task.py
eval_mm/tasks/task_registry.py
eval_mm/utils/__init__.py
eval_mm/utils/azure_client.py
eval_mm-0.4.1.dist-info/METADATA
eval_mm-0.4.1.dist-info/WHEEL
eval_mm-0.4.1.dist-info/licenses/LICENSE
eval_mm-0.4.1.dist-info/RECORD
