Metadata-Version: 2.4
Name: eval-mm
Version: 0.4.1
Summary: eval-mm is a tool for evaluating Multi-Modal Large Language Models.
Project-URL: Repository, https://github.com/llm-jp/llm-jp-eval-mm
Author-email: Silviase <koki.maeda@nlp.c.titech.ac.jp>, speed1313 <sugiura.issa.q29@kyoto-u.jp>
License-Expression: Apache-2.0
License-File: LICENSE
Requires-Python: >=3.12.1
Requires-Dist: av>=14.1.0
Requires-Dist: backoff>=2.2.1
Requires-Dist: datasets==2.18.0
Requires-Dist: emoji>=2.12.1
Requires-Dist: fugashi>=1.3.2
Requires-Dist: loguru>=0.7.3
Requires-Dist: openai>=1.42.0
Requires-Dist: python-dotenv>=1.0.1
Requires-Dist: requests>=2.32.3
Requires-Dist: rouge-score>=0.1.2
Requires-Dist: sacrebleu[ja]>=2.4.3
Requires-Dist: scipy>=1.15.1
Requires-Dist: torch>=2.5.1
Requires-Dist: types-requests>=2.32.0.20250328
Requires-Dist: unidic-lite>=1.0.8
Requires-Dist: webdataset>=0.2.111
